datarig/__init__.py
datarig/mixins.py
datarig/records.py
datarig/data/__init__.py
datarig-1.0.0.dist-info/LICENSE
datarig-1.0.0.dist-info/METADATA
datarig-1.0.0.dist-info/WHEEL
datarig-1.0.0.dist-info/top_level.txt
datarig-1.0.0.dist-info/RECORD
